strivelogger/__init__.py
strivelogger/logger_implementation.py
strivelogger/strive_logger.py
strivelogger/tracer_implementation.py
strivelogger/logger_implementations/console_logger.py
strivelogger/logger_implementations/null_logger.py
strivelogger/logger_implementations/python_logger.py
strivelogger/logger_implementations/uvicorn_logger.py
StriveLogger-1.1.0.dist-info/LICENSE
StriveLogger-1.1.0.dist-info/METADATA
StriveLogger-1.1.0.dist-info/WHEEL
StriveLogger-1.1.0.dist-info/top_level.txt
StriveLogger-1.1.0.dist-info/RECORD
