Metadata-Version: 2.1
Name: StriveLogger
Version: 1.1.0
Summary: A flexible logging abstraction layer
License: MIT License
Project-URL: Homepage, https://github.com/strivesolutions/strive-logger-py
Project-URL: Bug Tracker, https://github.com/strivesolutions/strive-logger-py/issues
Requires-Python: >=3.10
License-File: LICENSE
